README.rst
setup.py
linguafilter/__init__.py
linguafilter/common.py
linguafilter/gloss.py
linguafilter/ipa.py
linguafilter/ipa_mappings.py
linguafilter/lexicon.py
linguafilter/main.py
linguafilter/phonfeat.py
linguafilter/phonrule.py
linguafilter/test_common.py
linguafilter/test_gloss.py
linguafilter/test_ipa.py
linguafilter/test_ipa_mappings.py
linguafilter/test_lexicon.py
linguafilter/test_phonfeat.py
linguafilter/test_phonrule.py
linguafilter.egg-info/PKG-INFO
linguafilter.egg-info/SOURCES.txt
linguafilter.egg-info/dependency_links.txt
linguafilter.egg-info/entry_points.txt
linguafilter.egg-info/requires.txt
linguafilter.egg-info/top_level.txt