Metadata-Version: 1.1
Name: linguafilter
Version: 0.2.2
Summary: A pandoc filter adding support for various linguistics constructs
Home-page: https://github.com/benweedon/linguafilter
Author: Ben Weedon
Author-email: ben.weedon@outlook.com
License: GPLv3
Keywords: language,linguistics,pandoc,filter,conlang,conlangs
Platform: UNKNOWN
Classifier: Development Status :: 3 - Alpha
Classifier: Environment :: Console
Classifier: Environment :: Plugins
Classifier: Programming Language :: Python :: 2
Classifier: Programming Language :: Python :: 2.7
Classifier: Programming Language :: Python :: 3
Classifier: Programming Language :: Python :: 3.2
Classifier: Programming Language :: Python :: 3.3
Classifier: Programming Language :: Python :: 3.4
Classifier: Programming Language :: Python :: 3.5
Classifier: Programming Language :: Python :: 3.6
Classifier: Intended Audience :: Developers
Classifier: Intended Audience :: Other Audience
Classifier: License :: OSI Approved :: GNU General Public License v3 (GPLv3)
Classifier: Topic :: Other/Nonlisted Topic
